tfctl/__init__.py
tfctl/tfctl.py
tfctl-1.2.9.dist-info/licenses/LICENSE
tfctl-1.2.9.dist-info/METADATA
tfctl-1.2.9.dist-info/WHEEL
tfctl-1.2.9.dist-info/entry_points.txt
tfctl-1.2.9.dist-info/top_level.txt
tfctl-1.2.9.dist-info/RECORD
